{
    "name": "Luigelo Davila",
    "initials": "LDV",
    "description":  "Software Engineer with a strong development background and growing expertise in information security.",
    "summary": "As a Full Stack Developer. I've experience with microservices projects using FastAPI and .NET. I'm also a Computer Science student at Maastricht University and pursuing a Master's at Lomonosov Moscow State University. I hold CIW Web Developer and Agile with Atlassian Jira certifications, and founded Ldvloper, a software solutions team.",
    "email": "luigelo@ldvloper.com",
    "url": "https://ldvloper.com",
    "avatarUrl": "https://avatars.githubusercontent.com/u/53850824?v=4",
    "linkedinUrl": "https://www.linkedin.com/in/luigelo-davila/",
    "githubUsername": "@luigi-dv",
    "githubUrl": "https://github.com/Luigi-DV",
    "location": "Heerlen, Netherlands",
    "skills": [
      "Python",
      "JavaScript",
      "TypeScript",
      "C#",
      "Java",
      "HTML",
      "CSS",
      "SQL",
      "NoSQL",
      "Docker",
      "Kubernetes",
      "AWS",
      "Azure",
      "GCP",
      "CI/CD",
      "Git",
      "Jira",
      "Agile",
      "Scrum",
      "Kanban",
      "TDD",
      "BDD",
      "DDD",
      "SOLID",
      "Design Patterns",
      "Microservices",
      "MVC",
      "REST",
      "GraphQL",
      "WebSockets",
      "React",
      "Redux",
      "Angular",
      "Vue",
      "Node.js",
      "Express",
      "FastAPI",
      "Flask",
      "ASP.NET",
      "ASP.NET Core",
      "Entity Framework",
      "Django",
      "Spring Boot",
      "JUnit",
      "Jest",
      "Pytest",
      "Mocha",
      "Chai",
      "Jasmine",
      "Cypress",
      "Selenium",
      "Jenkins",
      "CircleCI",
      "TravisCI",
      "GitLab CI/CD",
      "GitHub Actions",
      "Azure DevOps",
      "Terraform",
      "Ansible",
      "Chef",
      "Puppet",
      "Kubernetes",
      "Helm",
      "Kustomize",
      "AWS",
      "Azure",
      "GCP",
      "DigitalOcean",
      "Heroku",
      "Netlify",
      "Vercel",
      "Nginx",
      "Apache",
      "IIS",
      "MongoDB",
      "PostgreSQL",
      "MySQL",
      "Redis",
      "Elasticsearch",
      "RabbitMQ",
      "Kafka",
      "DynamoDB",
      "Firebase",
      "Auth0",
      "Okta",
      "Keycloak",
      "OAuth 2.0",
      "OpenID Connect",
      "JWT",
      "OpenAPI",
      "gRPC",
      "gRPC-Web",
      "gRPC-Gateway",
      "gRPC-Web Proxy",
      "gRPC Reflection",
      "gRPC Health Check",
      "gRPC Load Balancing"
    ],
    "image": "/images/profile-picture.jpg"
}